sra/__init__.py
sra/client.py
sra/daemon.py
sra/deploy.json
sra/server.py
sra/version.py
sra-0.3.4.dist-info/DESCRIPTION.rst
sra-0.3.4.dist-info/METADATA
sra-0.3.4.dist-info/RECORD
sra-0.3.4.dist-info/WHEEL
sra-0.3.4.dist-info/entry_points.txt
sra-0.3.4.dist-info/metadata.json
sra-0.3.4.dist-info/top_level.txt
