Metadata-Version: 2.0
Name: sra
Version: 0.3.4
Summary: A simple deploy tool
Home-page: https://github.com/samqiu/sra
Author: samqiu
Author-email: sam@samqiu.com
License: MIT
Keywords: deploy
Platform: UNKNOWN
Classifier: Development Status :: 3 - Alpha
Classifier: Intended Audience :: Developers
Classifier: Topic :: Software Development :: Build Tools
Classifier: License :: OSI Approved :: MIT License
Classifier: Programming Language :: Python :: 2
Classifier: Programming Language :: Python :: 2.6
Classifier: Programming Language :: Python :: 2.7
Classifier: Programming Language :: Python :: 3
Classifier: Programming Language :: Python :: 3.2
Classifier: Programming Language :: Python :: 3.3
Classifier: Programming Language :: Python :: 3.4
Classifier: Programming Language :: Python :: 3.5
Requires-Dist: requests (==2.9.1)
Requires-Dist: tornado (==4.3)
Requires-Dist: websocket-client (==0.34.0)
